randomcharactergenerator/__init__.py
randomcharactergenerator/code.py
randomcharactergenerator-0.0.5.dist-info/LICENSE.txt
randomcharactergenerator-0.0.5.dist-info/METADATA
randomcharactergenerator-0.0.5.dist-info/WHEEL
randomcharactergenerator-0.0.5.dist-info/top_level.txt
randomcharactergenerator-0.0.5.dist-info/RECORD
