Metadata-Version: 2.1
Name: randomcharactergenerator
Version: 0.0.5
Summary: A library which generates random character codes using the random module
Home-page: https://github.com/SupremeCoder1707/randomcharactergenerator
Author: HighlyIntelligentBeing
Author-email: highlyintelligentbeing1707@gmail.com
License: UNKNOWN
Platform: UNKNOWN
Classifier: Programming Language :: Python :: 3
Classifier: License :: OSI Approved :: MIT License
Classifier: Operating System :: OS Independent
Requires-Python: >=3.6
